scapy/VERSION
scapy/__init__.py
scapy/__main__.py
scapy/all.py
scapy/ansmachine.py
scapy/as_resolvers.py
scapy/asn1fields.py
scapy/asn1packet.py
scapy/automaton.py
scapy/autorun.py
scapy/base_classes.py
scapy/compat.py
scapy/config.py
scapy/consts.py
scapy/dadict.py
scapy/data.py
scapy/error.py
scapy/fields.py
scapy/interfaces.py
scapy/main.py
scapy/packet.py
scapy/pipetool.py
scapy/plist.py
scapy/pton_ntop.py
scapy/py.typed
scapy/route.py
scapy/route6.py
scapy/scapypipes.py
scapy/sendrecv.py
scapy/sessions.py
scapy/supersocket.py
scapy/themes.py
scapy/utils.py
scapy/utils6.py
scapy/volatile.py
scapy/arch/__init__.py
scapy/arch/common.py
scapy/arch/libpcap.py
scapy/arch/solaris.py
scapy/arch/unix.py
scapy/arch/bpf/__init__.py
scapy/arch/bpf/consts.py
scapy/arch/bpf/core.py
scapy/arch/bpf/pfroute.py
scapy/arch/bpf/supersocket.py
scapy/arch/linux/__init__.py
scapy/arch/linux/rtnetlink.py
scapy/arch/windows/__init__.py
scapy/arch/windows/native.py
scapy/arch/windows/structures.py
scapy/asn1/__init__.py
scapy/asn1/asn1.py
scapy/asn1/ber.py
scapy/asn1/mib.py
scapy/contrib/__init__.py
scapy/contrib/altbeacon.py
scapy/contrib/aoe.py
scapy/contrib/avs.py
scapy/contrib/bfd.py
scapy/contrib/bgp.py
scapy/contrib/bier.py
scapy/contrib/bp.py
scapy/contrib/cansocket.py
scapy/contrib/cansocket_native.py
scapy/contrib/cansocket_python_can.py
scapy/contrib/carp.py
scapy/contrib/cdp.py
scapy/contrib/chdlc.py
scapy/contrib/coap.py
scapy/contrib/concox.py
scapy/contrib/diameter.py
scapy/contrib/dtp.py
scapy/contrib/eddystone.py
scapy/contrib/eigrp.py
scapy/contrib/enipTCP.py
scapy/contrib/erspan.py
scapy/contrib/esmc.py
scapy/contrib/ethercat.py
scapy/contrib/etherip.py
scapy/contrib/exposure_notification.py
scapy/contrib/geneve.py
scapy/contrib/gtp.py
scapy/contrib/gtp_v2.py
scapy/contrib/gxrp.py
scapy/contrib/hicp.py
scapy/contrib/homeplugav.py
scapy/contrib/homepluggp.py
scapy/contrib/homeplugsg.py
scapy/contrib/http2.py
scapy/contrib/ibeacon.py
scapy/contrib/icmp_extensions.py
scapy-2.6.0rc2.dist-info/LICENSE
scapy-2.6.0rc2.dist-info/METADATA
scapy-2.6.0rc2.dist-info/WHEEL
scapy-2.6.0rc2.dist-info/entry_points.txt
scapy-2.6.0rc2.dist-info/top_level.txt
scapy-2.6.0rc2.dist-info/RECORD
