Metadata-Version: 2.1
Name: scapy
Version: 2.6.0rc2
Summary: Scapy: interactive packet manipulation tool
Author: Philippe BIONDI
Maintainer: Pierre LALET, Gabriel POTTER, Guillaume VALADON, Nils WEISS
License: GPL-2.0-only
Project-URL: Homepage, https://scapy.net
Project-URL: Download, https://github.com/secdev/scapy/tarball/master
Project-URL: Documentation, https://scapy.readthedocs.io
Project-URL: Source Code, https://github.com/secdev/scapy
Project-URL: Changelog, https://github.com/secdev/scapy/releases
Keywords: network
Classifier: Development Status :: 5 - Production/Stable
Classifier: Environment :: Console
Classifier: Intended Audience :: Developers
Classifier: Intended Audience :: Information Technology
Classifier: Intended Audience :: Science/Research
Classifier: Intended Audience :: System Administrators
Classifier: Intended Audience :: Telecommunications Industry
Classifier: License :: OSI Approved :: GNU General Public License v2 (GPLv2)
Classifier: Programming Language :: Python :: 3
Classifier: Programming Language :: Python :: 3 :: Only
Classifier: Programming Language :: Python :: 3.7
Classifier: Programming Language :: Python :: 3.8
Classifier: Programming Language :: Python :: 3.9
Classifier: Programming Language :: Python :: 3.10
Classifier: Programming Language :: Python :: 3.11
Classifier: Programming Language :: Python :: 3.12
Classifier: Programming Language :: Python :: 3.13
Classifier: Topic :: Security
Classifier: Topic :: System :: Networking
Classifier: Topic :: System :: Networking :: Monitoring
Requires-Python: <4,>=3.7
License-File: LICENSE
Provides-Extra: all
Requires-Dist: ipython ; extra == 'all'
Requires-Dist: pyx ; extra == 'all'
Requires-Dist: cryptography >=2.0 ; extra == 'all'
Requires-Dist: matplotlib ; extra == 'all'
Provides-Extra: cli
Requires-Dist: ipython ; extra == 'cli'
Provides-Extra: doc
Requires-Dist: sphinx >=7.0.0 ; extra == 'doc'
Requires-Dist: sphinx-rtd-theme >=1.3.0 ; extra == 'doc'
Requires-Dist: tox >=3.0.0 ; extra == 'doc'
